plumify/__about__.py
plumify/__init__.py
plumify-0.0.1.dist-info/METADATA
plumify-0.0.1.dist-info/WHEEL
plumify-0.0.1.dist-info/licenses/LICENSE
plumify-0.0.1.dist-info/licenses/LICENSE.txt
plumify-0.0.1.dist-info/RECORD
